otherworlds/__init__.py
otherworlds/console/__init__.py
otherworlds/data/NameExoWorlds.csv
otherworlds/data/NameExoWorlds.csv.license
otherworlds/exoplanets.py
otherworlds/klingon.py
otherworlds/main.py
otherworlds/utils.py
otherworlds-1.2.0.dist-info/LICENSE
otherworlds-1.2.0.dist-info/LICENSES/CC0-1.0.txt
otherworlds-1.2.0.dist-info/LICENSES/GPL-3.0-or-later.txt
otherworlds-1.2.0.dist-info/METADATA
otherworlds-1.2.0.dist-info/WHEEL
otherworlds-1.2.0.dist-info/entry_points.txt
otherworlds-1.2.0.dist-info/RECORD
